{
	"name": "bronze_prata_sap_ecc_ekko",
	"properties": {
		"activities": [
			{
				"name": "bronze_prata_sap_ecc_ekko",
				"type": "DatabricksNotebook",
				"dependsOn": [],
				"policy": {
					"timeout": "0.0:30:00",
					"retry": 0,
					"retryIntervalInSeconds": 30,
					"secureOutput": false,
					"secureInput": false
				},
				"userProperties": [],
				"typeProperties": {
					"notebookPath": "/02-PRATA/templates/template_bronze_prata",
					"baseParameters": {
						"input_path": "/camada_bronze/sap_ecc/ekko/",
						"input_name": "ekko",
						"input_format": "parquet",
						"input_options": "{}",
						"read_mode": "delta",
						"output_path": "/camada_prata/sap_ecc/ekko/",
						"output_name": "ekko",
						"output_options": "{\"delta.columnMapping.mode\": \"name\"}",
						"output_keys": "LIFNR"
					}
				},
				"linkedServiceName": {
					"referenceName": "dbrk_eco_ls",
					"type": "LinkedServiceReference"
				}
			}
		],
		"folder": {
			"name": "02_BRONZE_PRATA/SAP_ECC"
		},
		"annotations": [],
		"lastPublishTime": "2023-10-03T18:53:17Z"
	},
	"type": "Microsoft.DataFactory/factories/pipelines"
}